evolving/__init__.py
evolving/ascmds.py
evolving/evolving.py
evolving/helper.py
tests/__init__.py
tests/evolving.py
tests/helper.py
evolving-1.1.3.dist-info/LICENSE
evolving-1.1.3.dist-info/METADATA
evolving-1.1.3.dist-info/WHEEL
evolving-1.1.3.dist-info/top_level.txt
evolving-1.1.3.dist-info/RECORD
