Metadata-Version: 2.1
Name: evolving
Version: 1.1.3
Summary: trading api
Home-page: https://github.com/zetatez/evolving
Author: Lorenzo
Author-email: zetatez@icloud.com
License: UNKNOWN
Platform: UNKNOWN
Classifier: Programming Language :: Python :: 3.8
Classifier: License :: OSI Approved :: MIT License
Classifier: Operating System :: OS Independent
Requires-Python: >=3.8
Requires-Dist: requests
